[{"timestamp":1669708222227,"files":[{"filename":"bundle.43f3d.css","previous":446,"size":446,"diff":0},{"filename":"bundle.*****.esm.js","previous":8285,"size":8283,"diff":-2},{"filename":"polyfills.*****.esm.js","previous":2181,"size":2181,"diff":0},{"filename":"route-home.chunk.c46db.css","previous":251,"size":251,"diff":0},{"filename":"route-home.chunk.*****.esm.js","previous":45143,"size":27677,"diff":-17466},{"filename":"route-profile.chunk.141aa.css","previous":78,"size":78,"diff":0},{"filename":"route-profile.chunk.*****.esm.js","previous":1483,"size":1483,"diff":0},{"filename":"sw-esm.js","previous":10981,"size":10978,"diff":-3},{"filename":"sw.js","previous":10975,"size":10977,"diff":2},{"filename":"bundle.66022.js","previous":8326,"size":0,"diff":-8326},{"filename":"polyfills.34206.js","previous":2281,"size":2281,"diff":0},{"filename":"route-home.chunk.9fd1a.js","previous":46043,"size":0,"diff":-46043},{"filename":"route-profile.chunk.96604.js","previous":1966,"size":1966,"diff":0},{"filename":"index.html","previous":890,"size":888,"diff":-2},{"filename":"200.html","previous":662,"size":659,"diff":-3},{"filename":"bundle.d8aad.js","previous":0,"size":8325,"diff":8325},{"filename":"route-home.chunk.6e965.js","previous":0,"size":28544,"diff":28544}]},{"timestamp":1669708130168,"files":[{"filename":"ssr-build/ssr-bundle.59e09.css","previous":751,"size":0,"diff":-751},{"filename":"ssr-build/ssr-bundle.js","previous":55725,"size":0,"diff":-55725},{"filename":"bundle.43f3d.css","previous":0,"size":446,"diff":446},{"filename":"bundle.*****.esm.js","previous":0,"size":8285,"diff":8285},{"filename":"polyfills.*****.esm.js","previous":0,"size":2181,"diff":2181},{"filename":"route-home.chunk.c46db.css","previous":0,"size":251,"diff":251},{"filename":"route-home.chunk.*****.esm.js","previous":0,"size":45143,"diff":45143},{"filename":"route-profile.chunk.141aa.css","previous":0,"size":78,"diff":78},{"filename":"route-profile.chunk.*****.esm.js","previous":0,"size":1483,"diff":1483},{"filename":"sw-esm.js","previous":0,"size":10981,"diff":10981},{"filename":"sw.js","previous":0,"size":10975,"diff":10975},{"filename":"bundle.66022.js","previous":0,"size":8326,"diff":8326},{"filename":"polyfills.34206.js","previous":0,"size":2281,"diff":2281},{"filename":"route-home.chunk.9fd1a.js","previous":0,"size":46043,"diff":46043},{"filename":"route-profile.chunk.96604.js","previous":0,"size":1966,"diff":1966},{"filename":"index.html","previous":0,"size":890,"diff":890},{"filename":"200.html","previous":0,"size":662,"diff":662}]}]
